{"expire":1718261713,"response":"{\n    \"id\": 1,\n    \"title\": \"\u041d\u0430\u0447\u0430\u043b\u043e\",\n    \"slug\": \"homepage\",\n    \"category_id\": 1,\n    \"cover_photo\": \"\",\n    \"active\": 1,\n    \"editable\": false,\n    \"url\": \"https:\\\/\\\/otto-artists.com\\\/bg\\\/homepage\",\n    \"private\": false,\n    \"seo_title\": \"OTTO. Platform for artists &amp; businesses\",\n    \"seo_tags\": \"\",\n    \"seo_description\": \"All talents are in one place. OTTO. Platform - home for everyone. Conection between artists and businesses. Find or post jobs. Find models, actors, designers, photographers and many other art talents.\",\n    \"banners\": [],\n    \"popups\": [],\n    \"surveys\": [],\n    \"category\": {\n        \"id\": 1,\n        \"parent_id\": 0,\n        \"title\": \"\u041e\u0441\u043d\u043e\u0432\u043d\u0438 \u0441\u0442\u0440\u0430\u043d\u0438\u0446\u0438\",\n        \"slug\": \"page-categories\",\n        \"position\": \"1\",\n        \"active\": \"1\"\n    }\n}","url":"https:\/\/devcore.myexpozy.com\/api\/pages\/1?resolution=10x10"}